hyperdb/__init__.py
hyperdb/_global.py
hyperdb/base.py
hyperdb/draw.py
hyperdb/hypergraph.py
hyperdb/templates/hypergraph_viewer.html
hypergraph_db-0.3.0.dist-info/METADATA
hypergraph_db-0.3.0.dist-info/WHEEL
hypergraph_db-0.3.0.dist-info/licenses/LICENSE
hypergraph_db-0.3.0.dist-info/RECORD
