Metadata-Version: 2.4
Name: hypergraph-db
Version: 0.3.0
Summary: A Lightweight Hypergraph Database with hypergraph visualization.
Project-URL: Homepage, https://github.com/iMoonLab/Hypergraph-DB
Project-URL: Repository, https://github.com/iMoonLab/Hypergraph-DB
Project-URL: Issues, https://github.com/iMoonLab/Hypergraph-DB/issues
Author-email: Yifan Feng <evanfeng97@qq.com>
License: Apache-2.0
License-File: LICENSE
Keywords: database,hypergraph,visualization
Classifier: Development Status :: 4 - Beta
Classifier: Intended Audience :: Developers
Classifier: Intended Audience :: Education
Classifier: Intended Audience :: Science/Research
Classifier: License :: OSI Approved :: Apache Software License
Classifier: Operating System :: OS Independent
Classifier: Programming Language :: Python :: 3.10
Classifier: Programming Language :: Python :: 3.11
Classifier: Programming Language :: Python :: 3.12
Classifier: Topic :: Scientific/Engineering
Classifier: Topic :: Scientific/Engineering :: Artificial Intelligence
Classifier: Topic :: Scientific/Engineering :: Mathematics
Classifier: Topic :: Software Development
Classifier: Topic :: Software Development :: Libraries
Classifier: Topic :: Software Development :: Libraries :: Python Modules
Requires-Python: >=3.10
